dnd/__init__.py
dnd/pkg.py
danger_noodle-0.1.7.dist-info/LICENSE
danger_noodle-0.1.7.dist-info/METADATA
danger_noodle-0.1.7.dist-info/WHEEL
danger_noodle-0.1.7.dist-info/entry_points.txt
danger_noodle-0.1.7.dist-info/top_level.txt
danger_noodle-0.1.7.dist-info/RECORD
