Metadata-Version: 2.1
Name: danger-noodle
Version: 0.1.7
Summary: Danger Noodle: Python package manager for npm assets
Home-page: https://gitlab.com/leopardm/dnd
Author: Michael Leopard
Author-email: mleopard@gitlab.com
License: UNKNOWN
Platform: UNKNOWN
Requires-Dist: bs4
Requires-Dist: progress
Requires-Dist: cursor
